dash_nivo/AreaBump.py
dash_nivo/DashNivo.py
dash_nivo/ResponsiveCircle.py
dash_nivo/__init__.py
dash_nivo/_imports_.py
dash_nivo/dash_nivo.min.js
dash_nivo/dash_nivo.min.js.map
dash_nivo/metadata.json
dash_nivo/package-info.json
dash_nivo-0.0.1.dist-info/LICENSE
dash_nivo-0.0.1.dist-info/METADATA
dash_nivo-0.0.1.dist-info/WHEEL
dash_nivo-0.0.1.dist-info/top_level.txt
dash_nivo-0.0.1.dist-info/RECORD
