Metadata-Version: 2.1
Name: dash_nivo
Version: 0.0.1
Summary: nivo integration for plotly
Author: pipinstallpython <pipinstallpython@gmail.com>
License: MIT
Classifier: Framework :: Dash
License-File: LICENSE
